ovos_media_plugin_spotify/__init__.py
ovos_media_plugin_spotify/audio.py
ovos_media_plugin_spotify/auth.py
ovos_media_plugin_spotify/autoconfigure.py
ovos_media_plugin_spotify/spotify_client.py
ovos_media_plugin_spotify/spotifyd.py
ovos_media_plugin_spotify/version.py
ovos_media_plugin_spotify-0.2.7.dist-info/licenses/LICENSE
ovos_media_plugin_spotify-0.2.7.dist-info/METADATA
ovos_media_plugin_spotify-0.2.7.dist-info/WHEEL
ovos_media_plugin_spotify-0.2.7.dist-info/entry_points.txt
ovos_media_plugin_spotify-0.2.7.dist-info/top_level.txt
ovos_media_plugin_spotify-0.2.7.dist-info/RECORD
