Metadata-Version: 2.4
Name: ovos_media_plugin_spotify
Version: 0.2.7
Summary: spotify plugin for ovos
Home-page: https://github.com/OpenVoiceOS/ovos-media-plugin-spotify
Author: JarbasAi
Author-email: jarbasai@mailfence.com
License: Apache-2.0
Keywords: ovos audio video OCP plugin
License-File: LICENSE
Requires-Dist: spotipy
Requires-Dist: ovos-plugin-manager<3.0.0,>=0.0.26
Requires-Dist: ovos-utils>=0.5.0
Dynamic: author
Dynamic: author-email
Dynamic: description
Dynamic: description-content-type
Dynamic: home-page
Dynamic: keywords
Dynamic: license
Dynamic: license-file
Dynamic: requires-dist
Dynamic: summary
